{
    "scenarios": {
        "1": {
            "title": "Первый контакт",
            "description": "Вы встречаетесь с потенциальным клиентом впервые. Ваша задача - установить контакт и выявить потребности в топливных картах и сопутствующих услугах.",
            "theory": {
                "title": "Основы первого контакта с клиентом",
                "content": [
                    "1. Установление контакта:",
                    "- Представьтесь и уточните, правильно ли вы понимаете цель встречи",
                    "- Проявите искренний интерес к автопарку клиента",
                    "- Используйте открытые вопросы для начала диалога",
                    "",
                    "2. Выявление потребностей:",
                    "- Узнайте о текущих расходах на топливо",
                    "- Выясните проблемы с текущим обслуживанием",
                    "- Определите потребности в дополнительных услугах",
                    "",
                    "3. Типичные ошибки:",
                    "- Слишком ранний переход к презентации топливных карт",
                    "- Обсуждение цены в начале разговора",
                    "- Игнорирование потребностей клиента"
                ]
            },
            "steps": [
                {
                    "clientMessage": "Здравствуйте! Мы ищем решение для оптимизации расходов на топливо.",
                    "options": [
                        {
                            "text": "Расскажите подробнее о вашем автопарке и текущих расходах на топливо.",
                            "score": 10,
                            "nextMessage": "У нас 15 автомобилей, сейчас заправляемся на разных АЗС, сложно контролировать расходы.",
                            "comment": "Правильно! Вы начали с выявления потребностей клиента, что позволяет лучше понять его ситуацию и предложить подходящее решение."
                        },
                        {
                            "text": "У нас есть отличное решение с топливными картами! Давайте я расскажу о наших преимуществах.",
                            "score": 5,
                            "nextMessage": "Хорошо, но сначала хотелось бы понять, как это будет работать в нашем случае...",
                            "comment": "Не совсем верно. Не стоит сразу переходить к презентации продукта, не выяснив потребности клиента."
                        },
                        {
                            "text": "Какой у вас бюджет на топливо в месяц?",
                            "score": 0,
                            "nextMessage": "Мне кажется, вы слишком рано спрашиваете о бюджете...",
                            "comment": "Неправильно. Обсуждение бюджета в начале разговора может отпугнуть клиента."
                        }
                    ]
                },
                {
                    "clientMessage": "У нас 15 автомобилей, сейчас заправляемся на разных АЗС, сложно контролировать расходы.",
                    "options": [
                        {
                            "text": "Понятно. Какие конкретные проблемы возникают при текущей системе заправок?",
                            "score": 10,
                            "nextMessage": "Сложно отслеживать расходы по каждому водителю, много времени уходит на сбор чеков и отчетность.",
                            "comment": "Правильно! Вы продолжаете выявлять конкретные потребности клиента, что поможет предложить точное решение."
                        },
                        {
                            "text": "Наши топливные карты решат все ваши проблемы!",
                            "score": 5,
                            "nextMessage": "Хотелось бы услышать конкретные примеры...",
                            "comment": "Не совсем верно. Слишком общие утверждения без конкретики могут вызвать недоверие у клиента."
                        }
                    ]
                }
            ]
        },
        "2": {
            "title": "Работа с возражениями",
            "description": "Клиент высказывает сомнения по поводу топливных карт. Ваша задача - грамотно отработать возражения.",
            "theory": {
                "title": "Техники работы с возражениями",
                "content": [
                    "1. Типы возражений:",
                    "- Возражения по цене топлива",
                    "- Возражения по срокам внедрения",
                    "- Возражения по качеству обслуживания",
                    "- Возражения по необходимости",
                    "",
                    "2. Алгоритм работы с возражениями:",
                    "- Выслушайте возражение полностью",
                    "- Уточните детали",
                    "- Признайте правоту клиента",
                    "- Предложите решение",
                    "",
                    "3. Ключевые принципы:",
                    "- Не спорьте с клиентом",
                    "- Используйте технику 'Да, и...'",
                    "- Фокусируйтесь на экономии, а не на цене топлива"
                ]
            },
            "steps": [
                {
                    "clientMessage": "У вас цена на топливо выше, чем на обычных АЗС.",
                    "options": [
                        {
                            "text": "Давайте посмотрим на общую экономию с учетом отсрочки платежа и дополнительных услуг.",
                            "score": 10,
                            "nextMessage": "Хорошо, расскажите подробнее о дополнительных услугах.",
                            "comment": "Правильно! Вы переводите разговор с цены на общую ценность, что помогает клиенту увидеть выгоду."
                        },
                        {
                            "text": "Могу предложить скидку на топливо.",
                            "score": 3,
                            "nextMessage": "А что насчет качества топлива?",
                            "comment": "Не совсем верно. Сразу предлагать скидку - это уступка, которая может снизить ценность продукта."
                        }
                    ]
                }
            ]
        },
        "3": {
            "title": "Закрытие сделки",
            "description": "Вы провели презентацию топливных карт, и клиент проявляет интерес. Пора закрывать сделку.",
            "theory": {
                "title": "Техники закрытия сделки",
                "content": [
                    "1. Признаки готовности к закрытию:",
                    "- Клиент спрашивает о процессе подключения",
                    "- Проявляет интерес к срокам",
                    "- Спрашивает о следующих шагах",
                    "",
                    "2. Методы закрытия:",
                    "- Альтернативное закрытие",
                    "- Закрытие на уступке",
                    "- Закрытие на срочности",
                    "",
                    "3. Работа с сомнениями:",
                    "- Выявление истинных причин сомнений",
                    "- Предложение тестового периода",
                    "- Гарантии и поддержка"
                ]
            },
            "steps": [
                {
                    "clientMessage": "Решение выглядит интересным. Что дальше?",
                    "options": [
                        {
                            "text": "Предлагаю начать с тестового периода на 2-3 автомобилях.",
                            "score": 10,
                            "nextMessage": "Это хорошая идея. Когда можем начать?",
                            "comment": "Правильно! Предложение тестового периода снижает риски для клиента и позволяет быстрее начать сотрудничество."
                        },
                        {
                            "text": "Давайте подпишем договор на весь автопарк.",
                            "score": 5,
                            "nextMessage": "Не слишком ли это поспешно?",
                            "comment": "Не совсем верно. Слишком быстрый переход к полному внедрению может вызвать сомнения у клиента."
                        }
                    ]
                }
            ]
        },
        "4": {
            "title": "Работа с конкурентом",
            "description": "Клиент уже использует топливные карты конкурента. Ваша задача - показать преимущества вашего решения.",
            "theory": {
                "title": "Стратегии работы с клиентами конкурентов",
                "content": [
                    "1. Анализ конкурента:",
                    "- Изучите сильные и слабые стороны конкурента",
                    "- Определите уникальные преимущества вашего продукта",
                    "- Подготовьте сравнение по ключевым параметрам",
                    "",
                    "2. Тактика переговоров:",
                    "- Не критикуйте конкурента",
                    "- Фокусируйтесь на дополнительных услугах",
                    "- Предложите тестовый период",
                    "",
                    "3. Работа с переходом:",
                    "- Обеспечьте плавный переход",
                    "- Предложите обучение сотрудников",
                    "- Гарантируйте поддержку в процессе перехода"
                ]
            },
            "steps": [
                {
                    "clientMessage": "Мы уже используем топливные карты вашего конкурента. Зачем нам менять?",
                    "options": [
                        {
                            "text": "Расскажите, какие услуги конкурента вы используете и что вас не устраивает?",
                            "score": 10,
                            "nextMessage": "В целом всё работает, но есть проблемы с отчетностью и поддержкой.",
                            "comment": "Правильно! Вы выявляете болевые точки клиента, что поможет показать преимущества вашего решения."
                        },
                        {
                            "text": "Наше решение лучше, потому что у нас больше АЗС в сети.",
                            "score": 2,
                            "nextMessage": "А конкретнее? Какие именно преимущества?",
                            "comment": "Неправильно. Общие утверждения без конкретики не убедительны."
                        }
                    ]
                }
            ]
        },
        "5": {
            "title": "Техническая консультация",
            "description": "Клиент задает технические вопросы о системе. Ваша задача - профессионально ответить на них.",
            "theory": {
                "title": "Проведение технической консультации",
                "content": [
                    "1. Подготовка к консультации:",
                    "- Изучите техническую документацию",
                    "- Подготовьте примеры использования",
                    "- Продумайте возможные вопросы",
                    "",
                    "2. Проведение консультации:",
                    "- Используйте понятный язык",
                    "- Приводите конкретные примеры",
                    "- Демонстрируйте работу системы",
                    "",
                    "3. Работа с техническими вопросами:",
                    "- Уточняйте детали вопроса",
                    "- Предлагайте несколько вариантов решения",
                    "- При необходимости привлекайте технических специалистов"
                ]
            },
            "steps": [
                {
                    "clientMessage": "Как работает система мониторинга расходов?",
                    "options": [
                        {
                            "text": "Расскажите, какие параметры вам важно отслеживать, и я подробно объясню, как работает система.",
                            "score": 10,
                            "nextMessage": "Нам нужно контролировать расходы по водителям и маршрутам.",
                            "comment": "Правильно! Вы выясняете детали потребностей клиента, что позволит предложить точное решение."
                        },
                        {
                            "text": "У нас есть онлайн-кабинет с подробной статистикой.",
                            "score": 5,
                            "nextMessage": "А как это будет работать в нашем случае?",
                            "comment": "Не совсем верно. Общий ответ без учета специфики клиента может вызвать сомнения."
                        }
                    ]
                }
            ]
        },
        "6": {
            "title": "Работа с бюджетом",
            "description": "Клиент ограничен в бюджете. Ваша задача - найти оптимальное решение.",
            "theory": {
                "title": "Работа с бюджетными ограничениями",
                "content": [
                    "1. Анализ бюджета:",
                    "- Выясните реальные возможности клиента",
                    "- Определите приоритетные потребности",
                    "- Рассчитайте экономию",
                    "",
                    "2. Стратегии работы:",
                    "- Предложите поэтапное подключение",
                    "- Разделите услуги на базовые и дополнительные",
                    "- Рассмотрите варианты финансирования",
                    "",
                    "3. Дополнительные возможности:",
                    "- Специальные условия для новых клиентов",
                    "- Программы лояльности",
                    "- Возможность масштабирования"
                ]
            },
            "steps": [
                {
                    "clientMessage": "Наш бюджет на топливо ограничен 500 000 рублей в месяц.",
                    "options": [
                        {
                            "text": "Давайте обсудим, какие услуги критически важны для вашего бизнеса, и подберем оптимальное решение.",
                            "score": 10,
                            "nextMessage": "Нам нужен базовый пакет: топливные карты и отчетность.",
                            "comment": "Правильно! Вы фокусируетесь на приоритетных потребностях клиента, что поможет найти решение в рамках бюджета."
                        },
                        {
                            "text": "Могу предложить урезанный пакет услуг.",
                            "score": 3,
                            "nextMessage": "А что именно будет в этом пакете?",
                            "comment": "Не совсем верно. Лучше сначала понять потребности клиента, а потом уже говорить о вариантах решения."
                        }
                    ]
                }
            ]
        },
        "7": {
            "title": "Финальный тест",
            "description": "Комплексная практика по продаже топливных карт. Вам предстоит провести полный цикл продажи от первого контакта до закрытия сделки.",
            "theory": {
                "title": "Комплексная практика продаж",
                "content": [
                    "1. Структура практики:",
                    "- Первый контакт и выявление потребностей",
                    "- Презентация решения",
                    "- Работа с возражениями",
                    "- Закрытие сделки",
                    "",
                    "2. Ключевые моменты:",
                    "- Используйте все изученные техники",
                    "- Адаптируйте подход под ситуацию",
                    "- Следите за уровнем доверия клиента",
                    "",
                    "3. Критерии оценки:",
                    "- Качество выявления потребностей",
                    "- Эффективность работы с возражениями",
                    "- Успешность закрытия сделки",
                    "- Профессионализм в общении"
                ]
            },
            "steps": [
                {
                    "clientMessage": "Здравствуйте! Мы транспортная компания, ищем способ оптимизировать расходы на топливо.",
                    "options": [
                        {
                            "text": "Расскажите, пожалуйста, о вашей компании и текущей системе заправок.",
                            "score": 10,
                            "nextMessage": "У нас 25 грузовых автомобилей, сейчас заправляемся на разных АЗС, сложно контролировать расходы и собирать отчетность.",
                            "comment": "Правильно! Вы начали с выявления потребностей, что позволит предложить оптимальное решение."
                        },
                        {
                            "text": "У нас есть отличное решение с топливными картами!",
                            "score": 5,
                            "nextMessage": "Хорошо, но сначала расскажите о вашей компании...",
                            "comment": "Не совсем верно. Не стоит сразу переходить к презентации, не выяснив потребности клиента."
                        }
                    ]
                },
                {
                    "clientMessage": "У нас 25 грузовых автомобилей, сейчас заправляемся на разных АЗС, сложно контролировать расходы и собирать отчетность.",
                    "options": [
                        {
                            "text": "Понятно. Какие конкретные проблемы возникают при текущей системе?",
                            "score": 10,
                            "nextMessage": "Много времени уходит на сбор чеков, сложно отслеживать расходы по водителям, бывают случаи нецелевого использования топлива.",
                            "comment": "Правильно! Вы углубляетесь в детали проблем, что поможет предложить точное решение."
                        },
                        {
                            "text": "Наши топливные карты решат все эти проблемы!",
                            "score": 5,
                            "nextMessage": "А как именно? Хотелось бы услышать подробности...",
                            "comment": "Не совсем верно. Лучше сначала полностью понять проблемы клиента."
                        }
                    ]
                },
                {
                    "clientMessage": "Много времени уходит на сбор чеков, сложно отслеживать расходы по водителям, бывают случаи нецелевого использования топлива.",
                    "options": [
                        {
                            "text": "Предлагаю рассмотреть наше решение. У нас есть топливные карты с лимитами по водителям, онлайн-отчетностью и мониторингом в реальном времени.",
                            "score": 10,
                            "nextMessage": "Звучит интересно. А как это будет работать на практике?",
                            "comment": "Правильно! Вы предлагаете решение, которое точно отвечает выявленным потребностям."
                        },
                        {
                            "text": "Давайте я расскажу о всех наших услугах.",
                            "score": 5,
                            "nextMessage": "Хотелось бы услышать только то, что решает наши проблемы...",
                            "comment": "Не совсем верно. Лучше фокусироваться на конкретных проблемах клиента."
                        }
                    ]
                },
                {
                    "clientMessage": "Звучит интересно. А как это будет работать на практике?",
                    "options": [
                        {
                            "text": "Давайте я подробно расскажу о системе. Каждому водителю выдается персональная карта с установленным лимитом. Все транзакции отображаются в онлайн-кабинете в реальном времени.",
                            "score": 10,
                            "nextMessage": "А что насчет цены на топливо? У вас она выше, чем на обычных АЗС.",
                            "comment": "Правильно! Вы детально объясняете работу системы, что повышает доверие клиента."
                        },
                        {
                            "text": "Всё очень просто, просто выдаете карты водителям.",
                            "score": 3,
                            "nextMessage": "Мне кажется, вы что-то умалчиваете...",
                            "comment": "Не совсем верно. Нужно быть более подробным в объяснении."
                        }
                    ]
                },
                {
                    "clientMessage": "А что насчет цены на топливо? У вас она выше, чем на обычных АЗС.",
                    "options": [
                        {
                            "text": "Давайте посмотрим на общую экономию. У нас есть отсрочка платежа до 30 дней, а также дополнительные услуги: мониторинг, отчетность, аналитика. Это позволит сократить расходы на администрирование и предотвратить нецелевое использование топлива.",
                            "score": 10,
                            "nextMessage": "Хорошо, а как начать работу с вами?",
                            "comment": "Правильно! Вы переводите разговор с цены на общую ценность и экономию."
                        },
                        {
                            "text": "Могу предложить скидку на топливо.",
                            "score": 3,
                            "nextMessage": "А что насчет качества топлива?",
                            "comment": "Не совсем верно. Лучше говорить о комплексной выгоде."
                        }
                    ]
                },
                {
                    "clientMessage": "Хорошо, а как начать работу с вами?",
                    "options": [
                        {
                            "text": "Предлагаю начать с тестового периода на 5 автомобилях. Это позволит вам оценить все преимущества системы. Для начала работы нужны только реквизиты компании и список автомобилей.",
                            "score": 10,
                            "nextMessage": "Отлично! Давайте начнем с тестового периода.",
                            "comment": "Правильно! Вы предлагаете конкретный план действий и минимизируете риски для клиента."
                        },
                        {
                            "text": "Давайте подпишем договор на весь автопарк.",
                            "score": 5,
                            "nextMessage": "Не слишком ли это поспешно?",
                            "comment": "Не совсем верно. Лучше начать с тестового периода."
                        }
                    ]
                }
            ]
        }
    }
} 